{
  "id": 9629,
  "source": "Nautilus",
  "title": "How Video Calling Worked Almost 100 Years Ago",
  "url": "https://nautil.us/how-video-calling-worked-almost-100-years-ago-1279577/",
  "published_at": "2026-04-07T18:35:53Z",
  "fetched_at": "2026-04-08T02:40:26.228085+00:00",
  "author": "Jake Currie",
  "summary": "<p>We’ve come a long way since then</p>\n<p>The post <a href=\"https://nautil.us/how-video-calling-worked-almost-100-years-ago-1279577/\">How Video Calling Worked Almost 100 Years Ago</a> appeared first on <a href=\"https://nautil.us\">Nautilus</a>.</p>",
  "full_text": "If you’re in your early 20s, you haven’t lived in a world without the widespread ability to have a video chat with someone halfway around the globe. Of course, there was a time when instantaneous conversations over video were relegated to the pages of science fiction. \n\nThe first video call took place on this day in 1927 between Commerce Secretary Herbert Hoover in Washington, D.C. and AT&T officials in New York City. It represented the culmination of half a century of technological advances. \n\nDreams of transmitting images over long distances began shortly after the advent of the telephone. In 1898, just two decades after Alexander Graham Bell’s marvelous invention, rumors of the development of a “telectroscope” spread, with a New York Times headline describing it as “a scheme for the transmission of colored rays.”\n\nVERY EARLY VIDEO: This prototype videophone from Bell Labs, dates to as early as 1927. It could only send video images one way, but was still the first hesitant step toward the ready video calling of the modern era. Photo courtesy of Marcin Wichary / Wikipedia.\n\nWhile there was no such invention, 1898 also saw a real leap in transmitting images via electricity with the invention of the “telediagraph.” A precursor to the modern fax machine, this device could transmit drawings over telegraph wires that were reproduced with a mechanical stylus. Less than a decade later, the wirephoto, used by newspapers, could perform the same feat by digitizing photographs using perforated paper. \n\nAT&T had their own version of a fax machine, and it was this technology that powered the historic video call in 1927. Called the “ikonophone” (from the Greek words for image and sound), their device was an electromechanical system that used a spinning disk to produce moving images at a rate of 18 frames per second. \n\nObviously, this early video phone had significant limitations. For starters, it was incredibly cumbersome, occupying about half a room, and the system needed a closed circuit linking Washington, D.C. to New York City. Though it conveyed two-way audio, it only transmitted choppy, monochromatic video images one-way. Still, it was a historic feat, and AT&T followed up three years and two days later with the first demonstration of a two-way video call. \n\nRead more: “Why I Built a Dumb Cell Phone with a Rotary Dial”\n\nIt wasn’t the only invention that propelled video phones forward in 1927, however. Five months later, Philo Farnsworth successfully transmitted the first image—a straight line—to a receiver in another room using cutting-edge cathode ray tube technology. With the widespread adoption of television in the coming decades, the dreams of video telephones seemed tantalizingly close. \n\nAT&T rolled out video phone booths in 1964 that required users to book a time for use, but discontinued them shortly after, citing insufficient demand. As television technology improved, the first videoconferencing services launched in the 1970s, but calls were expensive and they too failed to catch on. Technological advances in digital video in the 1980s and 1990s made video telephones smaller and person-to-person calls more feasible, but costs remained a barrier to widespread adoption. \n\nIt would take enormous strides forward in personal computing, video compression algorithms, and the internet to make the dreams of video phone calls a reality in the early 2000s. Now it’s so easy to initiate a video phone call that many of them are made accidentally. While the visionaries of the late 19th century were the first to imagine seeing and hearing real-time images of a loved one from across the planet, they never could have imagined the “butt-dial.” \n\nEnjoying Nautilus? Subscribe to our free newsletter.\n\nLead image: Sveta Khoruzhaia / Adobe Stock",
  "tags": [
    [
      "1000-words",
      "2026",
      "at&t",
      "bell labs",
      "call",
      "calling",
      "commerce",
      "d.c.",
      "dream",
      "early",
      "image",
      "new york city",
      "new york times",
      "phone",
      "technology",
      "transmit",
      "video",
      "washington",
      "widespread"
    ],
    [
      "technology",
      "video"
    ]
  ]
}