{
  "id": 9259,
  "source": "Longreads",
  "title": "Hallucinated Citations Are Polluting the Scientific Literature. What Can Be Done?",
  "url": "https://longreads.com/2026/04/06/hallucinated-citations-nature/",
  "published_at": "2026-04-06T18:27:13Z",
  "fetched_at": "2026-04-07T02:00:19.518405+00:00",
  "author": "Peter Rubin",
  "summary": "<div class=\"__iawmlf-post-loop-links\" style=\"display: none;\"></div>\n<p>When tools like Chat-GPT first gained widespread popularity, their tendency to hallucinate citations and references led to shame for scientists and attorneys who slipped those citations into their own briefs and studies. The pattern was troubling, but also avoidable—a little extra due diligence could weed out the confabulated referents. But as <em>Nature</em> finds in a collaboration with the screening company Grounded AI, scientific studies are increasingly filled with hallucinations that are slipperier than they appear. A title that matches up with a cited author&#8217;s area of study; co-authors that have published together previously; even volume/page numbers that sync to the supposed journal and date of publication. The result is a piece of microfiction, an imagined work of research that is fully plausible, but doesn&#8217;t actually exist. Remember when we bemoaned the erosion of &#8220;truth&#8221; just one s",
  "full_text": "When tools like Chat-GPT first gained widespread popularity, their tendency to hallucinate citations and references led to shame for scientists and attorneys who slipped those citations into their own briefs and studies. The pattern was troubling, but also avoidable—a little extra due diligence could weed out the confabulated referents. But as Nature finds in a collaboration with the screening company Grounded AI, scientific studies are increasingly filled with hallucinations that are slipperier than they appear. A title that matches up with a cited author’s area of study; co-authors that have published together previously; even volume/page numbers that sync to the supposed journal and date of publication. The result is a piece of microfiction, an imagined work of research that is fully plausible, but doesn’t actually exist. Remember when we bemoaned the erosion of “truth” just one short decade ago? As it turns out, we ain’t seen nothin’ yet.\n\nIn some cases, including in references in published articles, all of the component parts are made up, says Kathryn Weber-Boer, director of scientometrics at the London-based company Digital Science …. AI also hallucinates DOIs, both in references that are otherwise genuine as well as in fabricated ones, she adds.\n\nAI-generated references commonly combine fragments of genuine publications, say researchers who have studied the issue. Joe Shockman, co-founder and chief executive of Grounded AI, calls such references ‘Frankenstein’ citations, likening their assembly to that of the fictional monster. “It looks real to a human being, but is not actually a reference to a real thing,” says Shockman, who is based in Ashland, Oregon.\n\n \n\n \n\n \n\n More picks about science\n \n \n \n\n \n \n\n \n\n Mahmoud Mushtaha | Wired | March 23, 2026 | 5,667 words\n \n \n\n“In a place denied access to basic forensic technology—and where people disappear into Israeli detention—the fate of thousands remains unknown. One of them is an autistic teenager.”\n \n \n\n \n \n\n \n \n\n \n\n Sadiah Qureshi | Aeon | March 12, 2026 | 3,186 words \n \n\n“Technologies of preserving and reviving organisms are already redefining the meaning of life, death, and extinction itself.”\n \n \n\n \n \n\n \n \n\n \n\n Christopher Ingraham | Slate | March 12, 2026 | 5,320 words \n \n\n“At 42, with young kids, I got a devastating diagnosis. I knew I was in for a harrowing journey. I didn’t know quite what kind.”\n \n \n\n \n \n\n \n \n\n \n\n Sean Williams | Now Voyager | March 12, 2026 | 5,275 words\n \n \n\n“The search for the eighth wonder of the world.”\n \n \n\n \n \n\n \n \n\n \n\n Jacob Stern | The Atlantic | March 16, 2026 | 3,814 words \n \n\n“The odds of being struck by lightning in America in a given year are one in 1.2 million. How does the experience reorient a person’s sense of chance, of fate?”\n \n \n\n \n \n\n \n \n\n \n\n Kaitlyn Tiffany | The Atlantic | March 10, 2026 | 2,765 words \n \n\n“Why are some people convinced that nefarious experiments are happening in the distant Alaskan wilderness?”",
  "tags": [
    [
      "2026",
      "500-words",
      "ai",
      "america",
      "artificial intelligence",
      "ashland",
      "atlantic",
      "citation",
      "digital science",
      "editor's pick",
      "elizabeth quill",
      "genuine",
      "grounded",
      "grounded ai",
      "hallucinate",
      "kaitlyn tiffany",
      "london",
      "march",
      "miryam naddaf",
      "nature",
      "oregon",
      "publish",
      "reference",
      "science",
      "scientific",
      "slate",
      "wired",
      "word"
    ],
    [
      "editor's pick",
      "elizabeth quill",
      "miryam naddaf",
      "nature",
      "science"
    ]
  ]
}