{
  "id": 2561,
  "source": "Boing Boing",
  "title": "Palantir's Israel partnership began with Epstein introductions",
  "url": "https://boingboing.net/2026/03/10/palantirs-israel-partnership-began-with-epstein-introductions.html",
  "published_at": "2026-03-10T20:43:47Z",
  "fetched_at": "2026-03-10T23:20:12.971352+00:00",
  "author": "Ellsworth Toohey",
  "summary": "<a href=\"https://boingboing.net/2026/03/10/palantirs-israel-partnership-began-with-epstein-introductions.html\" rel=\"nofollow\" title=\"Palantir&#039;s Israel partnership began with Epstein introductions\"><img alt=\"Peter Thiel at Cambridge in 2024 / YouTube\" class=\"webfeedsFeaturedVisual wp-post-image\" height=\"853\" src=\"https://i0.wp.com/boingboing.net/wp-content/uploads/2026/03/thiel.jpg?fit=1200%2C853&amp;quality=60&amp;ssl=1\" style=\"display: block; margin: auto; margin-bottom: 5px;\" width=\"1200\" /></a><p>Palantir's strategic partnership with Israel's Ministry of Defense — the one supplying AI tools for the Gaza campaign and now the Iran war — traces back to introductions made by Jeffrey Epstein. DOJ-released documents show Epstein spent years connecting Peter Thiel with former Israeli prime minister and defense minister Ehud Barak, arranging at least six separate meetings because both men wanted to connect Silicon Valley with Israeli national security, <a href=\"https://jacobin.com/2026",
  "full_text": null,
  "tags": [
    "200-words",
    "began",
    "epstein",
    "introductions",
    "israel",
    "palantir",
    "partnership"
  ]
}