{
  "id": 250,
  "source": "Spiris Nyhetsrum",
  "title": "Ljusning för nyföretagandet under första halvåret",
  "url": "https://www.spiris.se/nyhetsrum/ljusning-for-nyforetagandet",
  "published_at": "2025-07-02",
  "fetched_at": "2026-03-04T13:23:53.600599+00:00",
  "author": null,
  "summary": "",
  "full_text": "– Det är en efterlängtad vändning efter flera års nedgång. Vi ser nu de första tecknen på en försiktig optimism bland blivande företagare. Det är oerhört viktigt för Sverige att fler väljer att förverkliga sina affärsidéer, säger Boo Gunnarson, företagarexpert på Spiris.\n\nUnder första halvåret 2025 registrerades 30 008 nya företag, vilket motsvarar en 2-procentig ökning jämfört med samma period 2024 då 29 384 företag startades. Även om uppgången är liten, bryts därmed den negativa trenden som präglat de senaste två åren. \n\n– Även om utvecklingen går åt rätt håll är det för tidigt att blåsa faran över. Svenska företagare står fortsatt inför stora utmaningar, och osäkerheten i omvärlden påverkar fortfarande viljan att starta företag. Därför är det avgörande att arbetet för enklare regler, stärkt trygghet, bättre finansieringsmöjligheter och ett mer gynnsamt entreprenörsklimat fortsätter, säger Boo Gunnarson.\n\nUtvecklingen varierar kraftigt mellan länen. Den största ökningen noteras på Gotland, där antalet nystartade företag steg med hela 27 procent under årets första sex månader. Därefter följer Dalarna, med en uppgång på 18 procent, samt Värmland och Södermanland där antalet nya bolag ökade med 17 respektive 15 procent. Samtidigt visar 7 av 21 län en negativ trend; störst nedgång syns i Östergötland och Gävleborg, minus 9 procent. Hittills i år kan dock 14 län notera en ökning för nyföretagandet.\n\n– Uppgången visar att entreprenörsandan lever, men också att det finns ett stort behov av långsiktiga reformer för att stärka svenskt nyföretagande. Nyföretagandet är otroligt viktigt för landets välfärd, var tredje skattekrona till kommunerna kommer från Sveriges företagare, säger Boo Gunnarson.\n\nFakta: Statistik över nyföretagandet på riks- och länsnivå\nI Sverige finns omkring en miljon företag registrerade hos Bolagsverket, varav merparten är små bolag med upp till nio anställda.\n\nTill siffrorna över nyföretagandet räknas de fyra vanligaste företagsformerna: aktiebolag, enskild näringsidkare, handelsbolag och kommanditbolag. Många enskilda näringsidkare är enbart registrerade hos Skatteverket och finns då inte med i Bolagsverkets statistik.\n\nAntal nyregistrerade företag första halvåret per län\n\nKälla: Bolagsverket\n\nNyregistrerade företag första halvåret 2021–2025",
  "tags": [
    "500-words",
    "Visa",
    "antalet",
    "företag",
    "första",
    "halvåret",
    "nyföretagandet",
    "sverige",
    "uppgången",
    "utvecklingen",
    "viktigt",
    "ökning"
  ]
}