{
  "id": 4348,
  "source": "Colossal",
  "title": "Restrained Emotions Simmer in Shinsuke Inoue’s Tender Wood Sculptures",
  "url": "https://www.thisiscolossal.com/2026/03/shinsuke-inoue-carved-wood-figures-sculptures/",
  "published_at": "2026-03-19T15:28:25Z",
  "fetched_at": "2026-03-19T17:00:23.360058+00:00",
  "author": "Kate Mothes",
  "summary": "<img alt=\"Restrained Emotions Simmer in Shinsuke Inoue&#8217;s Tender Wood Sculptures\" src=\"https://www.thisiscolossal.com/wp-content/uploads/2026/03/inoue-8.jpg\" />\n\n\n<p>Around a decade ago, <a href=\"https://www.instagram.com/shinsuke.inoue_art/\" rel=\"noreferrer noopener\" target=\"_blank\">Shinsuke Inoue</a> sourced a piece of Japanese wood and carved a depiction of his child, &#8220;wanting to preserve their likeness in three dimensions,&#8221; the artist tells Colossal. The affectionate expression of a loved one in sculptural form spurred a new passion for woodcarving, specifically with an emphasis on the human figure.</p>\n\n\n\n<p>Inoue&#8217;s pieces possess a kind of elemental groundedness or gravity that makes their restrained, sometimes hard-to-read expressions remarkably alluring. The figures often look straight ahead, and at the right angle, they make powerful eye contact with the viewer. And not unlike the way a small, meaningful smile or tiny frown can emerge from the most minut",
  "full_text": "Around a decade ago, Shinsuke Inoue sourced a piece of Japanese wood and carved a depiction of his child, “wanting to preserve their likeness in three dimensions,” the artist tells Colossal. The affectionate expression of a loved one in sculptural form spurred a new passion for woodcarving, specifically with an emphasis on the human figure.\n\nInoue’s pieces possess a kind of elemental groundedness or gravity that makes their restrained, sometimes hard-to-read expressions remarkably alluring. The figures often look straight ahead, and at the right angle, they make powerful eye contact with the viewer. And not unlike the way a small, meaningful smile or tiny frown can emerge from the most minute twitch of facial muscles, the striking characters are physically diminutive, but their inner emotional worlds are infinite.\n\nInoue works intuitively, allowing the material’s natural qualities to guide his hand. “I have virtually no idea what the finished piece will look like until I actually begin working with the wood,” he says. “As a result, the form often emerges as I carve, and I frequently change my plans midway through the process. Naturally, I keep the many failures a secret.” He always carves using hand tools and rarely titles the pieces.\n\nThe artist also references people he’s close to, along with strangers he passes on the street or sees photographs of, but his sculptures aren’t realistic depictions of specific individuals. Instead, Inoue concentrates on capturing a kind of universal expression of “the very essence of human existence… I hope that the inherent appeal of the wood, combined with its form and color, resonates to convey the essence of humanity itself.”\n\nSee more on Instagram.\n\n \n\n \n\nDo stories and artists like this matter to you? Become a Colossal Member now, and support independent arts publishing.",
  "tags": [
    "500-words",
    "artist",
    "essence",
    "expression",
    "human",
    "inoue",
    "kind",
    "piece",
    "restrained emotions",
    "sculptures",
    "shinsuke",
    "shinsuke inoue",
    "simmer",
    "tender wood",
    "wood"
  ]
}