{
  "id": 358,
  "source": "Klarna Newsroom",
  "title": "Klarna Announces Completion of Acquisition of BillPay",
  "url": "https://www.klarna.com/international/press/klarna-announces-completion-of-acquisition-of-billpay/",
  "published_at": "2017-09-13",
  "fetched_at": "2026-03-06T23:08:29.976336+00:00",
  "author": null,
  "summary": "",
  "full_text": "September 13 2017 – Klarna Bank AB (publ) today announces that the acquisition of German online payments company BillPay has been completed. This will strengthen Klarna’s position as one of the leading e-commerce payment providers in Europe and further accelerate its growth in Germany, Austria, Switzerland and The Netherlands.\n\nSebastian Siemiatkowski, co-founder and CEO of Klarna:\n\n“We are delighted that BillPay will now officially join Klarna Group. Combining our talent and technology will enable Klarna to continue to push the boundaries of innovation and product offering in existing and new markets with increased speed and confidence.”\n\nMarc Berg, Managing Director of Klarna DACH commented: “We are convinced that Klarna and BillPay together will now deliver even more attractive payment solutions to our merchants and customers in the region. We look forward to welcoming the experienced and dynamic BillPay team in Berlin into the Klarna Group.”\n\nBillPay currently partners with more than 5,000 merchants and allows online retailers to offer shoppers the ability to pay for ecommerce purchases via invoice, direct debit and installments. The German payment market is now divided into the payment categories invoice (such as Klarna), direct payments (e.g., Sofort), credit cards and wallets. According to the current ECC-Payment study*, invoice is the most popular payment method for consumers.\n\nAbout the Klarna Group\n\nKlarna is one of Europe’s largest banks and offers easy payment solutions for 60 million consumers and over 70,000 merchants. The company is now active in 18 markets with over 1600 employees. Klarna was founded in 2005 in Sweden with the idea of simplifying shopping. The core business of the company are pay after delivery, direct debit and installment payments. Today, Klarna is one of the fastest growing companies in Europe.\n\n \n\n________________________\n\n* ECC-Payment-Studie Vol. 21",
  "tags": [
    "acquisition",
    "announces",
    "billpay",
    "completion",
    "klarna"
  ]
}