{
  "id": 1488,
  "source": "The Public Domain Review",
  "title": "Last Order Dates for the Holiday Season - 2025",
  "url": "https://publicdomainreview.org/blog/2025/11/last-order-dates-for-christmas-2025",
  "published_at": "2025-11-12T13:15:00Z",
  "fetched_at": "2026-03-08T21:17:14.798389+00:00",
  "author": null,
  "summary": "<div><img src=\"https://pdr-assets.b-cdn.net//shop/nov-21-prints-00012.jpg?w=640\" /></div><p>The recommended cut-off dates to order from our shop by to ensure delivery in time for Dec 25th.</p>",
  "full_text": "🇺🇸 🇪🇺 US or EU: 8th Dec (Framed and Unframed)\n🇬🇧 UK: 30th Nov (Framed), 14th Dec (Unframed)\n🇦🇺 Australia: 30th Nov (Framed and Unframed)\n🇨🇦 Canada: 30th Nov (Framed), 8th Dec (Unframed)\n🌍 Everywhere else: 23rd Nov (Framed) and 30th Nov (Unframed)",
  "tags": [
    "200-words",
    "australia",
    "canada",
    "dates",
    "dec unframed",
    "everywhere",
    "holiday",
    "holiday season",
    "last order",
    "nov framed",
    "order",
    "season"
  ]
}